{
    "__comment": "Gym mod",
    "textures": {
        "0": "gymmod:blocks/dumbbelltex"
    },
    "elements": [
        {
            "name": "dumbbell_weight",
            "from": [ 2.0, 0.0, 5.0 ], 
            "to": [ 5.0, 6.0, 11.0 ], 
            "faces": {
                "north": { "texture": "#0", "uv": [ 0.0, 0.0, 3.0, 6.0 ] },
                "east": { "texture": "#0", "uv": [ 0.0, 0.0, 6.0, 6.0 ] },
                "south": { "texture": "#0", "uv": [ 0.0, 0.0, 3.0, 6.0 ] },
                "west": { "texture": "#0", "uv": [ 0.0, 0.0, 6.0, 6.0 ] },
                "up": { "texture": "#0", "uv": [ 0.0, 0.0, 3.0, 6.0 ] },
                "down": { "texture": "#0", "uv": [ 0.0, 0.0, 3.0, 6.0 ] }
            }
        },
        {
            "name": "dumbbell_weight_2",
            "from": [ 11.0, 0.0, 5.0 ], 
            "to": [ 14.0, 6.0, 11.0 ], 
            "faces": {
                "north": { "texture": "#0", "uv": [ 0.0, 0.0, 3.0, 6.0 ] },
                "east": { "texture": "#0", "uv": [ 0.0, 0.0, 6.0, 6.0 ] },
                "south": { "texture": "#0", "uv": [ 0.0, 0.0, 3.0, 6.0 ] },
                "west": { "texture": "#0", "uv": [ 0.0, 0.0, 6.0, 6.0 ] },
                "up": { "texture": "#0", "uv": [ 0.0, 0.0, 3.0, 6.0 ] },
                "down": { "texture": "#0", "uv": [ 0.0, 0.0, 3.0, 6.0 ] }
            }
        },
        {
            "name": "dumbbell_handle",
            "from": [ 4.0, 2.0, 7.0 ], 
            "to": [ 12.0, 4.0, 9.0 ], 
            "faces": {
                "north": { "texture": "#0", "uv": [ 0.0, 0.0, 8.0, 2.0 ] },
                "east": { "texture": "#0", "uv": [ 0.0, 0.0, 2.0, 2.0 ] },
                "south": { "texture": "#0", "uv": [ 0.0, 0.0, 8.0, 2.0 ] },
                "west": { "texture": "#0", "uv": [ 0.0, 0.0, 2.0, 2.0 ] },
                "up": { "texture": "#0", "uv": [ 0.0, 0.0, 8.0, 2.0 ] },
                "down": { "texture": "#0", "uv": [ 0.0, 0.0, 8.0, 2.0 ] }
            }
        },
        {
            "name": "dumbbell_weight_stabilizer",
            "from": [ 1.5, 1.0, 6.0 ], 
            "to": [ 3.5, 5.0, 10.0 ], 
            "faces": {
                "north": { "texture": "#0", "uv": [ 0.0, 0.0, 2.0, 4.0 ] },
                "east": { "texture": "#0", "uv": [ 0.0, 0.0, 4.0, 4.0 ] },
                "south": { "texture": "#0", "uv": [ 0.0, 0.0, 2.0, 4.0 ] },
                "west": { "texture": "#0", "uv": [ 0.0, 0.0, 4.0, 4.0 ] },
                "up": { "texture": "#0", "uv": [ 0.0, 0.0, 2.0, 4.0 ] },
                "down": { "texture": "#0", "uv": [ 0.0, 0.0, 2.0, 4.0 ] }
            }
        },
        {
            "name": "dumbbell_weight_stabilizer_2",
            "from": [ 12.5, 1.0, 6.0 ], 
            "to": [ 14.5, 5.0, 10.0 ], 
            "faces": {
                "north": { "texture": "#0", "uv": [ 0.0, 0.0, 2.0, 4.0 ] },
                "east": { "texture": "#0", "uv": [ 0.0, 0.0, 4.0, 4.0 ] },
                "south": { "texture": "#0", "uv": [ 0.0, 0.0, 2.0, 4.0 ] },
                "west": { "texture": "#0", "uv": [ 3.0, 2.0, 7.0, 6.0 ] },
                "up": { "texture": "#0", "uv": [ 0.0, 0.0, 2.0, 4.0 ] },
                "down": { "texture": "#0", "uv": [ 0.0, 0.0, 2.0, 9.0 ] }
            }
        },
        {
            "name": "stabilizator",
            "from": [ 0.5, 2.0, 7.0 ], 
            "to": [ 2.5, 4.0, 9.0 ], 
            "faces": {
                "north": { "texture": "#0", "uv": [ 0.0, 0.0, 2.0, 2.0 ] },
                "east": { "texture": "#0", "uv": [ 0.0, 0.0, 2.0, 2.0 ] },
                "south": { "texture": "#0", "uv": [ 0.0, 0.0, 2.0, 2.0 ] },
                "west": { "texture": "#0", "uv": [ 0.0, 0.0, 2.0, 2.0 ] },
                "up": { "texture": "#0", "uv": [ 0.0, 0.0, 2.0, 2.0 ] },
                "down": { "texture": "#0", "uv": [ 0.0, 0.0, 2.0, 2.0 ] }
            }
        },
        {
            "name": "stabilizator_2",
            "from": [ 13.5, 2.0, 7.0 ], 
            "to": [ 15.5, 4.0, 9.0 ], 
            "faces": {
                "north": { "texture": "#0", "uv": [ 4.0, 4.0, 6.0, 6.0 ] },
                "east": { "texture": "#0", "uv": [ 0.0, 0.0, 2.0, 2.0 ] },
                "south": { "texture": "#0", "uv": [ 0.0, 0.0, 2.0, 2.0 ] },
                "west": { "texture": "#0", "uv": [ 0.0, 0.0, 2.0, 2.0 ] },
                "up": { "texture": "#0", "uv": [ 0.0, 0.0, 2.0, 2.0 ] },
                "down": { "texture": "#0", "uv": [ 0.0, 0.0, 2.0, 2.0 ] }
            }
        }
    ]
}